TwistedYuYibuBianchengRumen/README.md
TwistedYuYibuBianchengRumen/__init__.py
TwistedYuYibuBianchengRumen/__main__.py
TwistedYuYibuBianchengRumen/file.epub
TwistedYuYibuBianchengRumen/index.html
TwistedYuYibuBianchengRumen/css/__init__.py
TwistedYuYibuBianchengRumen/css/annotations.css
TwistedYuYibuBianchengRumen/css/main.css
TwistedYuYibuBianchengRumen/css/normalize.css
TwistedYuYibuBianchengRumen/css/popup.css
TwistedYuYibuBianchengRumen/font/__init__.py
TwistedYuYibuBianchengRumen/font/fontello.eot
TwistedYuYibuBianchengRumen/font/fontello.svg
TwistedYuYibuBianchengRumen/font/fontello.ttf
TwistedYuYibuBianchengRumen/font/fontello.woff
TwistedYuYibuBianchengRumen/img/__init__.py
TwistedYuYibuBianchengRumen/img/annotator-glyph-sprite.png
TwistedYuYibuBianchengRumen/img/annotator-icon-sprite.png
TwistedYuYibuBianchengRumen/img/apple-touch-icon.png
TwistedYuYibuBianchengRumen/img/cancelfullscreen.png
TwistedYuYibuBianchengRumen/img/close.png
TwistedYuYibuBianchengRumen/img/fullscreen.png
TwistedYuYibuBianchengRumen/img/loader.gif
TwistedYuYibuBianchengRumen/img/menu-icon.png
TwistedYuYibuBianchengRumen/img/save.png
TwistedYuYibuBianchengRumen/img/saved.png
TwistedYuYibuBianchengRumen/img/settings-s.png
TwistedYuYibuBianchengRumen/img/settings.png
TwistedYuYibuBianchengRumen/img/star.png
TwistedYuYibuBianchengRumen/js/__init__.py
TwistedYuYibuBianchengRumen/js/epub.js
TwistedYuYibuBianchengRumen/js/epub.min.js
TwistedYuYibuBianchengRumen/js/epub.min.map
TwistedYuYibuBianchengRumen/js/hooks.min.js
TwistedYuYibuBianchengRumen/js/hooks.min.map
TwistedYuYibuBianchengRumen/js/reader.js
TwistedYuYibuBianchengRumen/js/reader.js.map
TwistedYuYibuBianchengRumen/js/reader.min.js
TwistedYuYibuBianchengRumen/js/reader.min.map
TwistedYuYibuBianchengRumen/js/hooks/__init__.py
TwistedYuYibuBianchengRumen/js/hooks/extensions/__init__.py
TwistedYuYibuBianchengRumen/js/hooks/extensions/highlight.js
TwistedYuYibuBianchengRumen/js/libs/__init__.py
twisted_yu_yibu_biancheng_rumen-2024.3.2.0.dist-info/METADATA
twisted_yu_yibu_biancheng_rumen-2024.3.2.0.dist-info/WHEEL
twisted_yu_yibu_biancheng_rumen-2024.3.2.0.dist-info/entry_points.txt
twisted_yu_yibu_biancheng_rumen-2024.3.2.0.dist-info/top_level.txt
twisted_yu_yibu_biancheng_rumen-2024.3.2.0.dist-info/RECORD
